setup.py
imagelib/__init__.py
imagelib/imagelib.py
imagelib.egg-info/PKG-INFO
imagelib.egg-info/SOURCES.txt
imagelib.egg-info/dependency_links.txt
imagelib.egg-info/top_level.txt