Metadata-Version: 1.1
Name: imagelib
Version: 0.2.0
Summary: A library for analyzing 10X Genomics data.
Home-page: https://github.com/antonybholmes/imagelib
Author: Antony B Holmes
Author-email: antony.b.holmes@gmail.com
License: UNKNOWN
Platform: UNKNOWN
Classifier: Programming Language :: Python :: 3
Classifier: License :: OSI Approved :: MIT License
Classifier: Operating System :: OS Independent
